goat_plugins/rugcheck/__init__.py
goat_plugins/rugcheck/parameters.py
goat_plugins/rugcheck/service.py
goat_sdk_plugin_rugcheck-0.1.3.dist-info/METADATA
goat_sdk_plugin_rugcheck-0.1.3.dist-info/WHEEL
goat_sdk_plugin_rugcheck-0.1.3.dist-info/RECORD
