Metadata-Version: 2.1
Name: goat-sdk-plugin-rugcheck
Version: 0.1.3
Summary: A Python rugcheck plugin for the GOAT SDK
Author: GOAT SDK Team
Requires-Python: >=3.9,<4.0
Classifier: Programming Language :: Python :: 3
Classifier: Programming Language :: Python :: 3.9
Classifier: Programming Language :: Python :: 3.10
Classifier: Programming Language :: Python :: 3.11
Classifier: Programming Language :: Python :: 3.12
Requires-Dist: aiohttp (>=3.8.4,<4.0.0)
Requires-Dist: goat-sdk (>=0.1.1,<0.2.0)
Requires-Dist: pydantic (>=2.0.0,<3.0.0)
